{
    "generated_utc":  "2026-04-03T11:04:49.8469271Z",
    "session_id":  "windbg-boot-registry-trace-20260403-140449",
    "collection_mode":  "evidence",
    "vm_path":  "H:\\Yedek\\VMs\\Win25H2Clean-B\\Win25H2Clean-B.vmx",
    "debugger_path":  "C:\\Program Files\\WindowsApps\\Microsoft.WinDbg_1.2603.20001.0_x64__8wekyb3d8bbwe\\amd64\\kd.exe",
    "trace_profile":  "symbols",
    "boot_mode":  "guest-restart",
    "break_on_connect_mode":  "bonc",
    "target_key":  null,
    "noise_budget_bytes":  262144,
    "noise_budget_event_limit":  100,
    "command_script":  "evidence/files/vm-tooling-staging/windbg-boot-registry-trace-20260403-140449/windbg-session-script.txt",
    "console_log":  "evidence/files/vm-tooling-staging/windbg-boot-registry-trace-20260403-140449/kd-console.log",
    "raw_log":  "evidence/files/vm-tooling-staging/windbg-boot-registry-trace-20260403-140449/windbg-registry-trace.log",
    "status":  "runner-ok",
    "steps":  [
                  "debugger-started",
                  "guest-restart-requested",
                  "vmtools-ready-after-restart",
                  "shell-healthy-after-restart",
                  "trace-finished"
              ],
    "shell_checks":  {
                         "explorer":  true,
                         "sihost":  true,
                         "shellhost":  true,
                         "ctfmon":  true
                     },
    "summary_path":  "evidence/files/vm-tooling-staging/windbg-boot-registry-trace-20260403-140449/summary.json",
    "results_path":  "evidence/files/vm-tooling-staging/windbg-boot-registry-trace-20260403-140449/results.json"
}
