{
    "start_time":  "2026-03-25T13:39:20.3696273+03:00",
    "sample_kind":  "custom",
    "sample_path":  "C:\\Tools\\Perf\\Procmon\\defender-custom-sample.exe",
    "eicar_path":  "C:\\Tools\\Perf\\Procmon\\defender-custom-sample.exe",
    "file_exists_after":  true,
    "mp_status_before":  {
                             "am_running_mode":  "Normal",
                             "antivirus_enabled":  true,
                             "realtime_enabled":  true,
                             "behavior_monitor_enabled":  true,
                             "ioav_enabled":  true,
                             "antispyware_enabled":  true
                         },
    "service_restart":  {
                            "requested":  false,
                            "attempted":  false,
                            "succeeded":  false,
                            "error":  null
                        },
    "mpcmdrun_exists":  true,
    "mpcmdrun_exit_code":  null,
    "mpcmdrun_timed_out":  true,
    "detection_event_count":  1,
    "hash_event_count":  0,
    "config_change_event_count":  0,
    "recent_event_ids":  [
                             1116
                         ],
    "hash_event_messages":  [

                            ]
}
