{
    "generated_utc":  "2026-03-28T22:53:46.7624669Z",
    "record_id":  "power.disable-cpu-idle-states",
    "session_id":  "cpu-idle-stepwise-20260329-013837",
    "snapshot_name":  "RegProbe-Baseline-20260328",
    "host_root":  "H:\\Temp\\vm-tooling-staging\\cpu-idle-stepwise-20260329-013837",
    "repo_root":  "evidence/files/vm-tooling-staging/cpu-idle-stepwise-20260329-013837",
    "guest_root":  "C:\\RegProbe-Diag\\cpu-idle-stepwise-20260329-013837",
    "guest_payload_path":  "C:\\RegProbe-Diag\\cpu-idle-stepwise-20260329-013837\\cpu-idle-stepwise-payload.ps1",
    "guest_etl_path":  "C:\\RegProbe-Diag\\cpu-idle-stepwise-20260329-013837\\cpu-idle-stepwise.etl",
    "completed_steps":  [
                            "A"
                        ],
    "next_step":  "B",
    "phase_status":  {
                         "A":  {
                                   "status":  "ok",
                                   "failed_stage":  null,
                                   "summary_file":  "step-a-summary.json"
                               },
                         "B":  {
                                   "status":  "failed",
                                   "failed_stage":  "wait-shell-post-reboot",
                                   "summary_file":  "step-b-summary.json"
                               }
                     },
    "artifacts":  {
                      "baseline":  "baseline.json",
                      "candidate":  "candidate.json",
                      "post_boot":  "post-boot.json",
                      "wpr_start":  "wpr-start.json",
                      "wpr_stop":  "wpr-stop.json",
                      "etl_check":  "etl-check.json",
                      "restore":  "restore.json",
                      "restore_after_boot":  "restore-after-boot.json",
                      "etl_placeholder":  "cpu-idle-stepwise.etl.md"
                  }
}
