[
    {
        "candidate_id":  "power.control.class1-initial-unpark-count",
        "family":  "power-control",
        "needle":  "Class1InitialUnparkCount",
        "hit_count":  1,
        "binaries":  [
                         {
                             "path":  "C:\\Windows\\System32\\ntoskrnl.exe",
                             "exists":  true,
                             "size":  12952992,
                             "ascii_match":  false,
                             "unicode_match":  true
                         },
                         {
                             "path":  "C:\\Windows\\System32\\powrprof.dll",
                             "exists":  true,
                             "size":  398160,
                             "ascii_match":  false,
                             "unicode_match":  false
                         }
                     ]
    },
    {
        "candidate_id":  "power.control.hibernate-enabled",
        "family":  "power-control",
        "needle":  "HibernateEnabled",
        "hit_count":  1,
        "binaries":  [
                         {
                             "path":  "C:\\Windows\\System32\\ntoskrnl.exe",
                             "exists":  true,
                             "size":  12952992,
                             "ascii_match":  true,
                             "unicode_match":  true
                         },
                         {
                             "path":  "C:\\Windows\\System32\\powrprof.dll",
                             "exists":  true,
                             "size":  398160,
                             "ascii_match":  false,
                             "unicode_match":  false
                         }
                     ]
    },
    {
        "candidate_id":  "power.control.hibernate-enabled-default",
        "family":  "power-control",
        "needle":  "HibernateEnabledDefault",
        "hit_count":  1,
        "binaries":  [
                         {
                             "path":  "C:\\Windows\\System32\\ntoskrnl.exe",
                             "exists":  true,
                             "size":  12952992,
                             "ascii_match":  false,
                             "unicode_match":  true
                         },
                         {
                             "path":  "C:\\Windows\\System32\\powrprof.dll",
                             "exists":  true,
                             "size":  398160,
                             "ascii_match":  false,
                             "unicode_match":  false
                         }
                     ]
    },
    {
        "candidate_id":  "power.control.lid-reliability-state",
        "family":  "power-control",
        "needle":  "LidReliabilityState",
        "hit_count":  1,
        "binaries":  [
                         {
                             "path":  "C:\\Windows\\System32\\ntoskrnl.exe",
                             "exists":  true,
                             "size":  12952992,
                             "ascii_match":  false,
                             "unicode_match":  true
                         },
                         {
                             "path":  "C:\\Windows\\System32\\powrprof.dll",
                             "exists":  true,
                             "size":  398160,
                             "ascii_match":  false,
                             "unicode_match":  false
                         }
                     ]
    },
    {
        "candidate_id":  "power.control.mf-buffering-threshold",
        "family":  "power-control",
        "needle":  "MfBufferingThreshold",
        "hit_count":  1,
        "binaries":  [
                         {
                             "path":  "C:\\Windows\\System32\\ntoskrnl.exe",
                             "exists":  true,
                             "size":  12952992,
                             "ascii_match":  false,
                             "unicode_match":  true
                         },
                         {
                             "path":  "C:\\Windows\\System32\\powrprof.dll",
                             "exists":  true,
                             "size":  398160,
                             "ascii_match":  false,
                             "unicode_match":  false
                         }
                     ]
    },
    {
        "candidate_id":  "power.control.perf-calculate-actual-utilization",
        "family":  "power-control",
        "needle":  "PerfCalculateActualUtilization",
        "hit_count":  1,
        "binaries":  [
                         {
                             "path":  "C:\\Windows\\System32\\ntoskrnl.exe",
                             "exists":  true,
                             "size":  12952992,
                             "ascii_match":  false,
                             "unicode_match":  true
                         },
                         {
                             "path":  "C:\\Windows\\System32\\powrprof.dll",
                             "exists":  true,
                             "size":  398160,
                             "ascii_match":  false,
                             "unicode_match":  false
                         }
                     ]
    },
    {
        "candidate_id":  "power.control.timer-rebase-threshold-on-drips-exit",
        "family":  "power-control",
        "needle":  "TimerRebaseThresholdOnDripsExit",
        "hit_count":  1,
        "binaries":  [
                         {
                             "path":  "C:\\Windows\\System32\\ntoskrnl.exe",
                             "exists":  true,
                             "size":  12952992,
                             "ascii_match":  false,
                             "unicode_match":  true
                         },
                         {
                             "path":  "C:\\Windows\\System32\\powrprof.dll",
                             "exists":  true,
                             "size":  398160,
                             "ascii_match":  false,
                             "unicode_match":  false
                         }
                     ]
    }
]
